flaskpp/__init__.py
flaskpp/__main__.py
flaskpp/_help.py
flaskpp/_init.py
flaskpp/babel.cfg
flaskpp/babel.py
flaskpp/cli.py
flaskpp/exceptions.py
flaskpp/flaskpp.py
flaskpp/i18n.py
flaskpp/module.py
flaskpp/socket.py
flaskpp/app/extensions.py
flaskpp/app/config/__init__.py
flaskpp/app/config/default.py
flaskpp/app/data/__init__.py
flaskpp/app/data/babel.py
flaskpp/app/data/fst_base.py
flaskpp/app/data/locales.json
flaskpp/app/data/noinit_translations.py
flaskpp/app/static/css/tailwind_raw.css
flaskpp/app/static/img/favicon.png
flaskpp/app/static/js/base.js
flaskpp/app/static/js/socket.js
flaskpp/app/templates/404.html
flaskpp/app/templates/base_example.html
flaskpp/app/templates/base_modal.html
flaskpp/app/templates/error.html
flaskpp/app/templates/flashing.html
flaskpp/app/templates/nav_link.html
flaskpp/app/templates/modals/confirm_modal.html
flaskpp/app/templates/modals/info_modal.html
flaskpp/app/utils/auto_nav.py
flaskpp/app/utils/processing.py
flaskpp/app/utils/translating.py
flaskpp/fpp_node/__init__.py
flaskpp/fpp_node/cli.py
flaskpp/fpp_node/fpp_vite.py
flaskpp/modules/__init__.py
flaskpp/modules/cli.py
flaskpp/modules/creator_templates.py
flaskpp/tailwind/__init__.py
flaskpp/tailwind/cli.py
flaskpp/tests/__init__.py
flaskpp/tests/cli.py
flaskpp/utils/__init__.py
flaskpp/utils/debugger.py
flaskpp/utils/run.py
flaskpp/utils/service_registry.py
flaskpp/utils/setup.py
flaskpp-0.3.5.dist-info/licenses/LICENSE
flaskpp-0.3.5.dist-info/METADATA
flaskpp-0.3.5.dist-info/WHEEL
flaskpp-0.3.5.dist-info/entry_points.txt
flaskpp-0.3.5.dist-info/top_level.txt
flaskpp-0.3.5.dist-info/RECORD
