Metadata-Version: 2.4
Name: flaskpp
Version: 0.3.5
Summary: A Flask based framework for fast and easy app creation. Experience the real power of Flask without boilerplate, but therefore a well balanced mix of magic and the default Flask framework.
Author-email: Pierre <pierre@growv-mail.org>
Requires-Python: >=3.10
License-File: LICENSE
Requires-Dist: flask
Requires-Dist: flask-sqlalchemy
Requires-Dist: flask-migrate
Requires-Dist: flask-limiter
Requires-Dist: flask-babelplus
Requires-Dist: flask-mailman
Requires-Dist: flask-security-too
Requires-Dist: flask-wtf
Requires-Dist: flask-caching
Requires-Dist: flask-smorest
Requires-Dist: flask-jwt-extended
Requires-Dist: flask-authlib-client
Requires-Dist: pymysql
Requires-Dist: python-dotenv
Requires-Dist: python-socketio[asgi]
Requires-Dist: authlib
Requires-Dist: uvicorn
Requires-Dist: asgiref
Requires-Dist: requests
Requires-Dist: redis
Requires-Dist: pytz
Requires-Dist: gitpython
Requires-Dist: tqdm
Requires-Dist: typer
Provides-Extra: test
Requires-Dist: pytest; extra == "test"
Requires-Dist: pytest-cov; extra == "test"
Requires-Dist: pytest-mock; extra == "test"
Dynamic: license-file
